ariadne/__about__.py
ariadne/__init__.py
ariadne/constants.py
ariadne/enums.py
ariadne/enums_default_values.py
ariadne/enums_values_visitor.py
ariadne/exceptions.py
ariadne/executable_schema.py
ariadne/extensions.py
ariadne/file_uploads.py
ariadne/format_error.py
ariadne/graphql.py
ariadne/inputs.py
ariadne/interfaces.py
ariadne/load_schema.py
ariadne/logger.py
ariadne/objects.py
ariadne/py.typed
ariadne/resolvers.py
ariadne/scalars.py
ariadne/schema_names.py
ariadne/schema_visitor.py
ariadne/subscriptions.py
ariadne/types.py
ariadne/unions.py
ariadne/utils.py
ariadne/wsgi.py
ariadne/asgi/__init__.py
ariadne/asgi/graphql.py
ariadne/asgi/handlers/__init__.py
ariadne/asgi/handlers/base.py
ariadne/asgi/handlers/graphql_transport_ws.py
ariadne/asgi/handlers/graphql_ws.py
ariadne/asgi/handlers/http.py
ariadne/contrib/__init__.py
ariadne/contrib/sse.py
ariadne/contrib/federation/__init__.py
ariadne/contrib/federation/interfaces.py
ariadne/contrib/federation/objects.py
ariadne/contrib/federation/schema.py
ariadne/contrib/federation/utils.py
ariadne/contrib/federation/definitions/fed_v1.0.graphql
ariadne/contrib/federation/definitions/fed_v2.0.graphql
ariadne/contrib/federation/definitions/fed_v2.1.graphql
ariadne/contrib/federation/definitions/fed_v2.2.graphql
ariadne/contrib/federation/definitions/fed_v2.3.graphql
ariadne/contrib/federation/definitions/fed_v2.4.graphql
ariadne/contrib/federation/definitions/fed_v2.5.graphql
ariadne/contrib/federation/definitions/fed_v2.6.graphql
ariadne/contrib/relay/__init__.py
ariadne/contrib/relay/arguments.py
ariadne/contrib/relay/connection.py
ariadne/contrib/relay/objects.py
ariadne/contrib/relay/types.py
ariadne/contrib/relay/utils.py
ariadne/contrib/tracing/__init__.py
ariadne/contrib/tracing/apollotracing.py
ariadne/contrib/tracing/copy_args.py
ariadne/contrib/tracing/opentelemetry.py
ariadne/contrib/tracing/opentracing.py
ariadne/contrib/tracing/utils.py
ariadne/explorer/__init__.py
ariadne/explorer/apollo.py
ariadne-0.26.0.dist-info/METADATA
ariadne-0.26.0.dist-info/WHEEL
ariadne-0.26.0.dist-info/licenses/LICENSE
ariadne-0.26.0.dist-info/RECORD
