Metadata-Version: 2.4
Name: ariadne
Version: 0.26.0
Summary: Ariadne is a Python library for implementing GraphQL servers.
Project-URL: Homepage, https://ariadnegraphql.org/
Project-URL: Repository, https://github.com/mirumee/ariadne
Project-URL: Bug Tracker, https://github.com/mirumee/ariadne/issues
Project-URL: Community, https://github.com/mirumee/ariadne/discussions
Project-URL: Twitter, https://twitter.com/AriadneGraphQL
Author-email: Mirumee Software <hello@mirumee.com>
License-Expression: BSD-3-Clause
License-File: LICENSE
Classifier: Development Status :: 4 - Beta
Classifier: Intended Audience :: Developers
Classifier: License :: OSI Approved :: BSD License
Classifier: Operating System :: OS Independent
Classifier: Programming Language :: Python
Classifier: Programming Language :: Python :: 3.9
Classifier: Programming Language :: Python :: 3.10
Classifier: Programming Language :: Python :: 3.11
Classifier: Programming Language :: Python :: 3.12
Classifier: Programming Language :: Python :: 3.13
Classifier: Topic :: Software Development :: Libraries :: Python Modules
Requires-Python: >=3.9
Requires-Dist: graphql-core<3.2.6,>=3.2.0
Requires-Dist: starlette<1.0,>0.17
Requires-Dist: typing-extensions>=3.6.0
Provides-Extra: dev
Requires-Dist: ipdb; extra == 'dev'
Provides-Extra: test
Requires-Dist: aiodataloader; extra == 'test'
Requires-Dist: freezegun; extra == 'test'
Requires-Dist: graphql-sync-dataloaders; (python_version > '3.7') and extra == 'test'
Requires-Dist: httpx; extra == 'test'
Requires-Dist: opentelemetry-api; extra == 'test'
Requires-Dist: opentracing; extra == 'test'
Requires-Dist: pytest; extra == 'test'
Requires-Dist: pytest-asyncio; extra == 'test'
Requires-Dist: pytest-benchmark; extra == 'test'
Requires-Dist: pytest-cov; extra == 'test'
Requires-Dist: pytest-mock; extra == 'test'
Requires-Dist: python-multipart>=0.0.5; extra == 'test'
Requires-Dist: syrupy; extra == 'test'
Requires-Dist: werkzeug; extra == 'test'
Provides-Extra: types
Requires-Dist: mypy>=1.0.0; extra == 'types'
